<markdown_skeleton_root>
  <block_element>
    <ArrayOfMarkdownBlockBase xmlns:xsi="http://www.w3.org/2001/XMLSchema-instance" xmlns:xsd="http://www.w3.org/2001/XMLSchema">
      <MarkdownBlockBase
        xsi:type="MarkdownListBlock"
        item_id="bfe4e7e0-effe-4afc-9547-1a3fb5f8f250"
        item_type="List"
        item_footer="&#xA;&#xA;&#xA;"
        trans_unit_id="bfe4e7e0-effe-4afc-9547-1a3fb5f8f250">
        <inner_list_items>
          <ListItem>
            <MarkdownParagraphBlock
              item_id="33215911-d128-472d-af10-d41ca8174a3f"
              item_type="NormalParagraph"
              item_footer=""
              trans_unit_id="33215911-d128-472d-af10-d41ca8174a3f">
              <Lines>
                <MarkdownLine>
                  <LineId>b4f34c1b-c1fb-4fff-a09b-6e5d0152d4f4</LineId>
                  <paragraph_segments>
                    <MarkdownSegment
                      trans_unit_id="101">
                      <SegmentId>b48338dd-067f-4039-9542-5bc9b60c3de7</SegmentId>
                      <InternalNormalItem
                        internal_item_id="1"
                        internal_item_parent_id="101"
                        trans_unit_id="101-1"
                        internal_item_type="Normal">
                        <internal_items />
                      </InternalNormalItem>
                      <MarkdownInternalBoldItem
                        internal_item_id="2"
                        internal_item_parent_id="101"
                        trans_unit_id="101-2"
                        internal_item_type="Bold">
                        <internal_items />
                        <internal_itatic_bold_item_type>Star</internal_itatic_bold_item_type>
                      </MarkdownInternalBoldItem>
                      <InternalNormalItem
                        internal_item_id="3"
                        internal_item_parent_id="101"
                        trans_unit_id="101-3"
                        internal_item_type="Normal">
                        <internal_items />
                      </InternalNormalItem>
                    </MarkdownSegment>
                  </paragraph_segments>
                  <PrefixWSLength>1</PrefixWSLength>
                  <SuffixWSLength>0</SuffixWSLength>
                </MarkdownLine>
              </Lines>
              <paragraph_segments>
                <MarkdownSegment
                  trans_unit_id="101">
                  <SegmentId>b48338dd-067f-4039-9542-5bc9b60c3de7</SegmentId>
                  <InternalNormalItem
                    internal_item_id="1"
                    internal_item_parent_id="101"
                    trans_unit_id="101-1"
                    internal_item_type="Normal">
                    <internal_items />
                  </InternalNormalItem>
                  <MarkdownInternalBoldItem
                    internal_item_id="2"
                    internal_item_parent_id="101"
                    trans_unit_id="101-2"
                    internal_item_type="Bold">
                    <internal_items />
                    <internal_itatic_bold_item_type>Star</internal_itatic_bold_item_type>
                  </MarkdownInternalBoldItem>
                  <InternalNormalItem
                    internal_item_id="3"
                    internal_item_parent_id="101"
                    trans_unit_id="101-3"
                    internal_item_type="Normal">
                    <internal_items />
                  </InternalNormalItem>
                </MarkdownSegment>
              </paragraph_segments>
            </MarkdownParagraphBlock>
            <Identifier>1.</Identifier>
            <IndentsLength>
              <int>0</int>
            </IndentsLength>
          </ListItem>
          <ListItem>
            <MarkdownParagraphBlock
              item_id="dd54cb6c-e01e-4b1d-8560-ae3bca003038"
              item_type="NormalParagraph"
              item_footer=""
              trans_unit_id="dd54cb6c-e01e-4b1d-8560-ae3bca003038">
              <Lines>
                <MarkdownLine>
                  <LineId>016522e7-4462-44cb-9bce-2ab3224f323d</LineId>
                  <paragraph_segments>
                    <MarkdownSegment
                      trans_unit_id="102">
                      <SegmentId>a5e40bd9-70d5-4583-97f9-293e94d16b34</SegmentId>
                      <InternalNormalItem
                        internal_item_id="1"
                        internal_item_parent_id="102"
                        trans_unit_id="102-1"
                        internal_item_type="Normal">
                        <internal_items />
                      </InternalNormalItem>
                      <MarkdownInternalBoldItem
                        internal_item_id="2"
                        internal_item_parent_id="102"
                        trans_unit_id="102-2"
                        internal_item_type="Bold">
                        <internal_items />
                        <internal_itatic_bold_item_type>Star</internal_itatic_bold_item_type>
                      </MarkdownInternalBoldItem>
                      <InternalNormalItem
                        internal_item_id="3"
                        internal_item_parent_id="102"
                        trans_unit_id="102-3"
                        internal_item_type="Normal">
                        <internal_items />
                      </InternalNormalItem>
                      <MarkdownInternalBoldItem
                        internal_item_id="4"
                        internal_item_parent_id="102"
                        trans_unit_id="102-4"
                        internal_item_type="Bold">
                        <internal_items />
                        <internal_itatic_bold_item_type>Star</internal_itatic_bold_item_type>
                      </MarkdownInternalBoldItem>
                      <InternalNormalItem
                        internal_item_id="5"
                        internal_item_parent_id="102"
                        trans_unit_id="102-5"
                        internal_item_type="Normal">
                        <internal_items />
                      </InternalNormalItem>
                      <MarkdownInternalBoldItem
                        internal_item_id="6"
                        internal_item_parent_id="102"
                        trans_unit_id="102-6"
                        internal_item_type="Bold">
                        <internal_items />
                        <internal_itatic_bold_item_type>Star</internal_itatic_bold_item_type>
                      </MarkdownInternalBoldItem>
                      <InternalNormalItem
                        internal_item_id="7"
                        internal_item_parent_id="102"
                        trans_unit_id="102-7"
                        internal_item_type="Normal">
                        <internal_items />
                      </InternalNormalItem>
                    </MarkdownSegment>
                  </paragraph_segments>
                  <PrefixWSLength>1</PrefixWSLength>
                  <SuffixWSLength>0</SuffixWSLength>
                </MarkdownLine>
              </Lines>
              <paragraph_segments>
                <MarkdownSegment
                  trans_unit_id="102">
                  <SegmentId>a5e40bd9-70d5-4583-97f9-293e94d16b34</SegmentId>
                  <InternalNormalItem
                    internal_item_id="1"
                    internal_item_parent_id="102"
                    trans_unit_id="102-1"
                    internal_item_type="Normal">
                    <internal_items />
                  </InternalNormalItem>
                  <MarkdownInternalBoldItem
                    internal_item_id="2"
                    internal_item_parent_id="102"
                    trans_unit_id="102-2"
                    internal_item_type="Bold">
                    <internal_items />
                    <internal_itatic_bold_item_type>Star</internal_itatic_bold_item_type>
                  </MarkdownInternalBoldItem>
                  <InternalNormalItem
                    internal_item_id="3"
                    internal_item_parent_id="102"
                    trans_unit_id="102-3"
                    internal_item_type="Normal">
                    <internal_items />
                  </InternalNormalItem>
                  <MarkdownInternalBoldItem
                    internal_item_id="4"
                    internal_item_parent_id="102"
                    trans_unit_id="102-4"
                    internal_item_type="Bold">
                    <internal_items />
                    <internal_itatic_bold_item_type>Star</internal_itatic_bold_item_type>
                  </MarkdownInternalBoldItem>
                  <InternalNormalItem
                    internal_item_id="5"
                    internal_item_parent_id="102"
                    trans_unit_id="102-5"
                    internal_item_type="Normal">
                    <internal_items />
                  </InternalNormalItem>
                  <MarkdownInternalBoldItem
                    internal_item_id="6"
                    internal_item_parent_id="102"
                    trans_unit_id="102-6"
                    internal_item_type="Bold">
                    <internal_items />
                    <internal_itatic_bold_item_type>Star</internal_itatic_bold_item_type>
                  </MarkdownInternalBoldItem>
                  <InternalNormalItem
                    internal_item_id="7"
                    internal_item_parent_id="102"
                    trans_unit_id="102-7"
                    internal_item_type="Normal">
                    <internal_items />
                  </InternalNormalItem>
                </MarkdownSegment>
              </paragraph_segments>
            </MarkdownParagraphBlock>
            <MarkdownParagraphBlock
              item_id="ec9c825a-0c1a-4efe-95cf-352769d2dbff"
              item_type="NormalParagraph"
              item_footer=""
              trans_unit_id="ec9c825a-0c1a-4efe-95cf-352769d2dbff">
              <Lines>
                <MarkdownLine>
                  <LineId>41795a50-988b-49cd-a7a9-ea43c36639d3</LineId>
                  <paragraph_segments>
                    <MarkdownSegment
                      trans_unit_id="103">
                      <SegmentId>71dfca77-7272-437f-80d6-68dd5b267623</SegmentId>
                      <ImageItem
                        internal_item_id="1"
                        internal_item_parent_id="103"
                        trans_unit_id="103-1"
                        internal_item_type="Image">
                        <internal_items />
                        <internal_Image_type>Inline</internal_Image_type>
                        <internal_link_text>Click Settings</internal_link_text>
                        <internal_link_url>./media/app-service-api-config-auth/clicksettings.png</internal_link_url>
                        <internal_link_title />
                      </ImageItem>
                    </MarkdownSegment>
                  </paragraph_segments>
                  <PrefixWSLength>1</PrefixWSLength>
                  <SuffixWSLength>0</SuffixWSLength>
                </MarkdownLine>
              </Lines>
              <paragraph_segments>
                <MarkdownSegment
                  trans_unit_id="103">
                  <SegmentId>71dfca77-7272-437f-80d6-68dd5b267623</SegmentId>
                  <ImageItem
                    internal_item_id="1"
                    internal_item_parent_id="103"
                    trans_unit_id="103-1"
                    internal_item_type="Image">
                    <internal_items />
                    <internal_Image_type>Inline</internal_Image_type>
                    <internal_link_text>Click Settings</internal_link_text>
                    <internal_link_url>./media/app-service-api-config-auth/clicksettings.png</internal_link_url>
                    <internal_link_title />
                  </ImageItem>
                </MarkdownSegment>
              </paragraph_segments>
            </MarkdownParagraphBlock>
            <MarkdownParagraphBlock
              item_id="8ef80deb-936f-4ef3-8746-c535e0d4d94b"
              item_type="NormalParagraph"
              item_footer=""
              trans_unit_id="8ef80deb-936f-4ef3-8746-c535e0d4d94b">
              <Lines>
                <MarkdownLine>
                  <LineId>bf167f51-6c85-4e9d-8539-3cf53a5b5f52</LineId>
                  <paragraph_segments>
                    <MarkdownSegment
                      trans_unit_id="104">
                      <SegmentId>ada4526c-5d54-4792-a159-f697c8366662</SegmentId>
                      <ImageItem
                        internal_item_id="1"
                        internal_item_parent_id="104"
                        trans_unit_id="104-1"
                        internal_item_type="Image">
                        <internal_items />
                        <internal_Image_type>Inline</internal_Image_type>
                        <internal_link_text>Click Application settings</internal_link_text>
                        <internal_link_url>./media/app-service-api-config-auth/clickbasicsettings.png</internal_link_url>
                        <internal_link_title />
                      </ImageItem>
                    </MarkdownSegment>
                  </paragraph_segments>
                  <PrefixWSLength>1</PrefixWSLength>
                  <SuffixWSLength>0</SuffixWSLength>
                </MarkdownLine>
              </Lines>
              <paragraph_segments>
                <MarkdownSegment
                  trans_unit_id="104">
                  <SegmentId>ada4526c-5d54-4792-a159-f697c8366662</SegmentId>
                  <ImageItem
                    internal_item_id="1"
                    internal_item_parent_id="104"
                    trans_unit_id="104-1"
                    internal_item_type="Image">
                    <internal_items />
                    <internal_Image_type>Inline</internal_Image_type>
                    <internal_link_text>Click Application settings</internal_link_text>
                    <internal_link_url>./media/app-service-api-config-auth/clickbasicsettings.png</internal_link_url>
                    <internal_link_title />
                  </ImageItem>
                </MarkdownSegment>
              </paragraph_segments>
            </MarkdownParagraphBlock>
            <Identifier>2.</Identifier>
            <IndentsLength>
              <int>0</int>
              <int>3</int>
              <int>3</int>
            </IndentsLength>
          </ListItem>
          <ListItem>
            <MarkdownParagraphBlock
              item_id="2297c2f3-451f-4074-871c-12eaa9772b84"
              item_type="NormalParagraph"
              item_footer=""
              trans_unit_id="2297c2f3-451f-4074-871c-12eaa9772b84">
              <Lines>
                <MarkdownLine>
                  <LineId>62f56803-17c3-47ca-a59b-6207cf1a2d98</LineId>
                  <paragraph_segments>
                    <MarkdownSegment
                      trans_unit_id="105">
                      <SegmentId>e2f120fd-863c-4538-8b7f-27f85484fcd2</SegmentId>
                      <InternalNormalItem
                        internal_item_id="1"
                        internal_item_parent_id="105"
                        trans_unit_id="105-1"
                        internal_item_type="Normal">
                        <internal_items />
                      </InternalNormalItem>
                      <MarkdownInternalBoldItem
                        internal_item_id="2"
                        internal_item_parent_id="105"
                        trans_unit_id="105-2"
                        internal_item_type="Bold">
                        <internal_items />
                        <internal_itatic_bold_item_type>Star</internal_itatic_bold_item_type>
                      </MarkdownInternalBoldItem>
                      <InternalNormalItem
                        internal_item_id="3"
                        internal_item_parent_id="105"
                        trans_unit_id="105-3"
                        internal_item_type="Normal">
                        <internal_items />
                      </InternalNormalItem>
                      <MarkdownInternalBoldItem
                        internal_item_id="4"
                        internal_item_parent_id="105"
                        trans_unit_id="105-4"
                        internal_item_type="Bold">
                        <internal_items />
                        <internal_itatic_bold_item_type>Star</internal_itatic_bold_item_type>
                      </MarkdownInternalBoldItem>
                      <InternalNormalItem
                        internal_item_id="5"
                        internal_item_parent_id="105"
                        trans_unit_id="105-5"
                        internal_item_type="Normal">
                        <internal_items />
                      </InternalNormalItem>
                      <MarkdownInternalBoldItem
                        internal_item_id="6"
                        internal_item_parent_id="105"
                        trans_unit_id="105-6"
                        internal_item_type="Bold">
                        <internal_items />
                        <internal_itatic_bold_item_type>Star</internal_itatic_bold_item_type>
                      </MarkdownInternalBoldItem>
                      <InternalNormalItem
                        internal_item_id="7"
                        internal_item_parent_id="105"
                        trans_unit_id="105-7"
                        internal_item_type="Normal">
                        <internal_items />
                      </InternalNormalItem>
                      <MarkdownInternalBoldItem
                        internal_item_id="8"
                        internal_item_parent_id="105"
                        trans_unit_id="105-8"
                        internal_item_type="Bold">
                        <internal_items />
                        <internal_itatic_bold_item_type>Star</internal_itatic_bold_item_type>
                      </MarkdownInternalBoldItem>
                      <InternalNormalItem
                        internal_item_id="9"
                        internal_item_parent_id="105"
                        trans_unit_id="105-9"
                        internal_item_type="Normal">
                        <internal_items />
                      </InternalNormalItem>
                    </MarkdownSegment>
                  </paragraph_segments>
                  <PrefixWSLength>1</PrefixWSLength>
                  <SuffixWSLength>0</SuffixWSLength>
                </MarkdownLine>
              </Lines>
              <paragraph_segments>
                <MarkdownSegment
                  trans_unit_id="105">
                  <SegmentId>e2f120fd-863c-4538-8b7f-27f85484fcd2</SegmentId>
                  <InternalNormalItem
                    internal_item_id="1"
                    internal_item_parent_id="105"
                    trans_unit_id="105-1"
                    internal_item_type="Normal">
                    <internal_items />
                  </InternalNormalItem>
                  <MarkdownInternalBoldItem
                    internal_item_id="2"
                    internal_item_parent_id="105"
                    trans_unit_id="105-2"
                    internal_item_type="Bold">
                    <internal_items />
                    <internal_itatic_bold_item_type>Star</internal_itatic_bold_item_type>
                  </MarkdownInternalBoldItem>
                  <InternalNormalItem
                    internal_item_id="3"
                    internal_item_parent_id="105"
                    trans_unit_id="105-3"
                    internal_item_type="Normal">
                    <internal_items />
                  </InternalNormalItem>
                  <MarkdownInternalBoldItem
                    internal_item_id="4"
                    internal_item_parent_id="105"
                    trans_unit_id="105-4"
                    internal_item_type="Bold">
                    <internal_items />
                    <internal_itatic_bold_item_type>Star</internal_itatic_bold_item_type>
                  </MarkdownInternalBoldItem>
                  <InternalNormalItem
                    internal_item_id="5"
                    internal_item_parent_id="105"
                    trans_unit_id="105-5"
                    internal_item_type="Normal">
                    <internal_items />
                  </InternalNormalItem>
                  <MarkdownInternalBoldItem
                    internal_item_id="6"
                    internal_item_parent_id="105"
                    trans_unit_id="105-6"
                    internal_item_type="Bold">
                    <internal_items />
                    <internal_itatic_bold_item_type>Star</internal_itatic_bold_item_type>
                  </MarkdownInternalBoldItem>
                  <InternalNormalItem
                    internal_item_id="7"
                    internal_item_parent_id="105"
                    trans_unit_id="105-7"
                    internal_item_type="Normal">
                    <internal_items />
                  </InternalNormalItem>
                  <MarkdownInternalBoldItem
                    internal_item_id="8"
                    internal_item_parent_id="105"
                    trans_unit_id="105-8"
                    internal_item_type="Bold">
                    <internal_items />
                    <internal_itatic_bold_item_type>Star</internal_itatic_bold_item_type>
                  </MarkdownInternalBoldItem>
                  <InternalNormalItem
                    internal_item_id="9"
                    internal_item_parent_id="105"
                    trans_unit_id="105-9"
                    internal_item_type="Normal">
                    <internal_items />
                  </InternalNormalItem>
                </MarkdownSegment>
              </paragraph_segments>
            </MarkdownParagraphBlock>
            <MarkdownParagraphBlock
              item_id="9af271ec-57d5-411f-9728-417f6af11708"
              item_type="NormalParagraph"
              item_footer="footer_not_set"
              trans_unit_id="9af271ec-57d5-411f-9728-417f6af11708">
              <Lines>
                <MarkdownLine>
                  <LineId>5ffcf326-ebb2-4749-ab95-d3d5a2891cef</LineId>
                  <paragraph_segments>
                    <MarkdownSegment
                      trans_unit_id="106">
                      <SegmentId>57360c3d-7cad-4443-8a28-7ab5d2aef485</SegmentId>
                      <ImageItem
                        internal_item_id="1"
                        internal_item_parent_id="106"
                        trans_unit_id="106-1"
                        internal_item_type="Image">
                        <internal_items />
                        <internal_Image_type>Inline</internal_Image_type>
                        <internal_link_text>Click Basic settings</internal_link_text>
                        <internal_link_url>./media/app-service-api-config-auth/setpublicauth.png</internal_link_url>
                        <internal_link_title />
                      </ImageItem>
                    </MarkdownSegment>
                  </paragraph_segments>
                  <PrefixWSLength>1</PrefixWSLength>
                  <SuffixWSLength>0</SuffixWSLength>
                </MarkdownLine>
              </Lines>
              <paragraph_segments>
                <MarkdownSegment
                  trans_unit_id="106">
                  <SegmentId>57360c3d-7cad-4443-8a28-7ab5d2aef485</SegmentId>
                  <ImageItem
                    internal_item_id="1"
                    internal_item_parent_id="106"
                    trans_unit_id="106-1"
                    internal_item_type="Image">
                    <internal_items />
                    <internal_Image_type>Inline</internal_Image_type>
                    <internal_link_text>Click Basic settings</internal_link_text>
                    <internal_link_url>./media/app-service-api-config-auth/setpublicauth.png</internal_link_url>
                    <internal_link_title />
                  </ImageItem>
                </MarkdownSegment>
              </paragraph_segments>
            </MarkdownParagraphBlock>
            <Identifier>3.</Identifier>
            <IndentsLength>
              <int>0</int>
              <int>3</int>
            </IndentsLength>
          </ListItem>
        </inner_list_items>
        <ListType>Number</ListType>
      </MarkdownBlockBase>
    </ArrayOfMarkdownBlockBase>
  </block_element>
  <references>
    <ArrayOfMarkdownLinkedReference xmlns:xsi="http://www.w3.org/2001/XMLSchema-instance" xmlns:xsd="http://www.w3.org/2001/XMLSchema" />
  </references>
</markdown_skeleton_root>